{"nodes": [{"id": "archive_ArchiveConverter", "label": "ArchiveConverter", "file_type": "code", "source_file": "sample/convt/apps/web/src/lib/converters/archive.ts", "source_location": "11:141", "source_url": null, "captured_at": null, "author": null, "contributor": null}, {"id": "archive_archiveConverter", "label": "archiveConverter", "file_type": "code", "source_file": "sample/convt/apps/web/src/lib/converters/archive.ts", "source_location": "143:143", "source_url": null, "captured_at": null, "author": null, "contributor": null}, {"id": "archive_createZip", "label": "createZip", "file_type": "code", "source_file": "sample/convt/apps/web/src/lib/converters/archive.ts", "source_location": "40:59", "source_url": null, "captured_at": null, "author": null, "contributor": null}, {"id": "archive_extractZip", "label": "extractZip", "file_type": "code", "source_file": "sample/convt/apps/web/src/lib/converters/archive.ts", "source_location": "61:124", "source_url": null, "captured_at": null, "author": null, "contributor": null}, {"id": "types_Converter_interface", "label": "Converter Interface", "file_type": "code", "source_file": "sample/convt/apps/web/src/lib/converters/archive.ts", "source_location": "3:9", "source_url": null, "captured_at": null, "author": null, "contributor": null}], "edges": [{"source": "archive_ArchiveConverter", "target": "types_Converter_interface", "relation": "implements", "confidence": "EXTRACTED", "confidence_score": 1.0, "source_file": "sample/convt/apps/web/src/lib/converters/archive.ts", "source_location": "11:11", "weight": 1.0}, {"source": "archive_ArchiveConverter", "target": "archive_createZip", "relation": "calls", "confidence": "EXTRACTED", "confidence_score": 1.0, "source_file": "sample/convt/apps/web/src/lib/converters/archive.ts", "source_location": "37:37", "weight": 1.0}, {"source": "archive_ArchiveConverter", "target": "archive_extractZip", "relation": "calls", "confidence": "EXTRACTED", "confidence_score": 1.0, "source_file": "sample/convt/apps/web/src/lib/converters/archive.ts", "source_location": "34:34", "weight": 1.0}, {"source": "archive_archiveConverter", "target": "archive_ArchiveConverter", "relation": "references", "confidence": "EXTRACTED", "confidence_score": 1.0, "source_file": "sample/convt/apps/web/src/lib/converters/archive.ts", "source_location": "143:143", "weight": 1.0}, {"source": "archive_extractZip", "target": "index_Converter", "relation": "shares_data_with", "confidence": "INFERRED", "confidence_score": 0.78, "source_file": "sample/convt/apps/web/src/lib/converters/archive.ts", "source_location": "118:123", "weight": 1.0}], "hyperedges": []}