{"nodes": [{"id": "last-updated_LastUpdated", "label": "LastUpdated", "file_type": "code", "source_file": "sample/convt/apps/web/src/components/seo/last-updated.tsx", "source_location": "4:24", "source_url": null, "captured_at": null, "author": null, "contributor": null}, {"id": "last-updated_getLastUpdatedISO", "label": "getLastUpdatedISO", "file_type": "code", "source_file": "sample/convt/apps/web/src/components/seo/last-updated.tsx", "source_location": "26:28", "source_url": null, "captured_at": null, "author": null, "contributor": null}], "edges": [], "hyperedges": []}